Metadata-Version: 2.0
Name: django-simple-help
Version: 0.6.1
Summary: Django reusable application providing page help
Home-page: https://github.com/DCOD-OpenSource/django-simple-help/
Author: Alexei Andrushievich
Author-email: vint21h@vint21h.pp.ua
License: MIT
Download-URL: https://github.com/DCOD-OpenSource/django-simple-help/archive/0.6.1.tar.gz
Platform: UNKNOWN
Classifier: Environment :: Plugins
Classifier: License :: OSI Approved :: MIT License
Classifier: Operating System :: Unix
Classifier: Programming Language :: Python :: 2.6
Classifier: Programming Language :: Python :: 2.7
Classifier: Programming Language :: Python :: 3
Classifier: Topic :: Utilities
Classifier: Framework :: Django :: 1.5
Classifier: Framework :: Django :: 1.6
Classifier: Framework :: Django :: 1.7
Classifier: Framework :: Django :: 1.8
Classifier: Framework :: Django :: 1.9
Classifier: Framework :: Django :: 1.10
Classifier: Framework :: Django :: 1.11
Requires-Dist: Django
Requires-Dist: django-annoying (==0.10.3)
Requires-Dist: django-wysiwyg-redactor (==0.5.1)
Provides-Extra: modeltranslation
Requires-Dist: django-modeltranslation (==0.12.1); extra == 'modeltranslation'
